liblabtest/__init__.py
liblabtest/sdk.py
liblabtest/setup.py
liblabtest/hooks/__init__.py
liblabtest/models/ApiCreateRequest.py
liblabtest/models/ApiGetApiBuilds200Response.py
liblabtest/models/ApiGetApiByOrgSlugAndApiSlug200Response.py
liblabtest/models/ApiGetApiDocs200Response.py
liblabtest/models/ApiGetApiMembers200Response.py
liblabtest/models/ApiGetApiSdks200Response.py
liblabtest/models/ApiGetApis200Response.py
liblabtest/models/ApiResponse.py
liblabtest/models/ApiUpdateRequest.py
liblabtest/models/ArtifactCreateRequest.py
liblabtest/models/ArtifactGetArtifacts200Response.py
liblabtest/models/ArtifactResponse.py
liblabtest/models/AuthChangePasswordRequest.py
liblabtest/models/AuthLoginRequest.py
liblabtest/models/AuthOneTimeLoginRequest.py
liblabtest/models/AuthRefreshTokenRequest.py
liblabtest/models/AuthRequest.py
liblabtest/models/AuthResetPasswordRequest.py
liblabtest/models/AuthSignupRequest.py
liblabtest/models/AuthTokenResponse.py
liblabtest/models/AuthVerifyEmailRequest.py
liblabtest/models/BuildBuildDocRequest.py
liblabtest/models/BuildBuildSdkRequest.py
liblabtest/models/BuildDocRequest.py
liblabtest/models/BuildGetBuilds200Response.py
liblabtest/models/BuildResponse.py
liblabtest/models/ChangePasswordRequest.py
liblabtest/models/CreateApiRequest.py
liblabtest/models/CreateArtifactRequest.py
liblabtest/models/CreateDocRequest.py
liblabtest/models/CreateOrgMemberRequest.py
liblabtest/models/CreateOrgRequest.py
liblabtest/models/CreateSdkBuildRequest.py
liblabtest/models/CreateSdkRequest.py
liblabtest/models/CreateTokenRequest.py
liblabtest/models/CreateTokenResponse.py
liblabtest/models/CreateUserRequest.py
liblabtest/models/DocCreateRequest.py
liblabtest/models/DocCreatedResponse.py
liblabtest/models/DocFindDocs200Response.py
liblabtest/models/DocResponse.py
liblabtest/models/DocUpdateRequest.py
liblabtest/models/EditOrgRequest.py
liblabtest/models/EditUserRequest.py
liblabtest/models/EventTrackRequest.py
liblabtest/models/GetTokenResponse.py
Liblabtest-1.0.6.dist-info/METADATA
Liblabtest-1.0.6.dist-info/WHEEL
Liblabtest-1.0.6.dist-info/top_level.txt
Liblabtest-1.0.6.dist-info/RECORD
