Metadata-Version: 2.1
Name: Liblabtest
Version: 1.0.6
Author-email: Example Author <author@example.com>
License: SEE LICENSE IN LICENSE
Project-URL: Homepage, https://github.com/pypa/sampleproject
Project-URL: Bug Tracker, https://github.com/pypa/sampleproject/issues
Classifier: Programming Language :: Python :: 3
Classifier: License :: OSI Approved :: MIT License
Classifier: Operating System :: OS Independent
Requires-Python: >=3.7
Requires-Dist: requests (==2.28.1)
Requires-Dist: http-exceptions (==0.2.10)
Requires-Dist: pytest (==7.1.2)
Requires-Dist: responses (==0.21.0)
